django_geosource/__init__.py
django_geosource/admin.py
django_geosource/app_settings.py
django_geosource/apps.py
django_geosource/callbacks.py
django_geosource/fields.py
django_geosource/mixins.py
django_geosource/models.py
django_geosource/parsers.py
django_geosource/permissions.py
django_geosource/serializers.py
django_geosource/signals.py
django_geosource/urls.py
django_geosource/views.py
django_geosource/celery/__init__.py
django_geosource/celery/schedulers.py
django_geosource/celery/tasks.py
django_geosource/management/__init__.py
django_geosource/management/commands/__init__.py
django_geosource/management/commands/resync_all_sources.py
django_geosource/migrations/0001_initial.py
django_geosource/migrations/0002_auto_20190524_1137.py
django_geosource/migrations/0003_auto_20190528_1629.py
django_geosource/migrations/0004_auto_20190529_1647.py
django_geosource/migrations/0005_auto_20190603_1506.py
django_geosource/migrations/0006_auto_20190612_1020.py
django_geosource/migrations/0007_commandsource.py
django_geosource/migrations/0008_source_settings.py
django_geosource/migrations/0009_source_slug.py
django_geosource/migrations/0010_wmtssource.py
django_geosource/migrations/0011_auto_20190628_1449.py
django_geosource/migrations/0012_field_level.py
django_geosource/migrations/0013_auto_20190709_1735.py
django_geosource/migrations/0014_auto_20190821_1648.py
django_geosource/migrations/0015_auto_20190927_1445.py
django_geosource/migrations/__init__.py
django_geosource/tests/__init__.py
django_geosource/tests/test_api.py
test_geosource/__init__.py
test_geosource/settings.py
test_geosource/urls.py
test_geosource/wsgi.py
django_geosource-0.3.1.dist-info/LICENCE.md
django_geosource-0.3.1.dist-info/METADATA
django_geosource-0.3.1.dist-info/WHEEL
django_geosource-0.3.1.dist-info/top_level.txt
django_geosource-0.3.1.dist-info/RECORD
