Metadata-Version: 2.1
Name: django-geosource
Version: 0.3.1
Summary: Django geographic asynchrone data sources loading
Home-page: https://github.com/Terralego/django-geosource.git
Author: Makina Corpus
Author-email: terralego-pypi@makina-corpus.com
License: UNKNOWN
Platform: UNKNOWN
Classifier: Environment :: Web Environment
Classifier: Framework :: Django
Classifier: Intended Audience :: Developers
Classifier: Topic :: Internet :: WWW/HTTP
Classifier: Topic :: Internet :: WWW/HTTP :: Dynamic Content
Classifier: License :: OSI Approved :: MIT License
Classifier: Natural Language :: English
Classifier: Operating System :: OS Independent
Classifier: Programming Language :: Python
Classifier: Programming Language :: Python :: 3.6
Classifier: Programming Language :: Python :: 3.7
Requires-Dist: Django (<3.0,>=2.2)
Requires-Dist: djangorestframework (<3.9,>=3.8)
Requires-Dist: django-polymorphic (<2.1,>=2.0)
Requires-Dist: celery (<4.4,>=4.3)
Requires-Dist: psycopg2 (>=2.7)
Requires-Dist: Fiona (<1.9,>=1.8)
